pycobi/__init__.py
pycobi/automated_continuation.py
pycobi/pycobi.py
pycobi/utility.py
pycobi_tests/__init__.py
pycobi_tests/conftest.py
pycobi_tests/test_odesystem.py
pycobi-0.9.1.dist-info/LICENSE
pycobi-0.9.1.dist-info/METADATA
pycobi-0.9.1.dist-info/WHEEL
pycobi-0.9.1.dist-info/top_level.txt
pycobi-0.9.1.dist-info/RECORD
