Metadata-Version: 2.1
Name: pycobi
Version: 0.9.1
Summary: Python tool for parameter continuation and bifurcation analysis
Home-page: UNKNOWN
Author: Richard Gast
Author-email: rgast@scripps.edu
License: GPL v3
Platform: UNKNOWN
Classifier: Programming Language :: Python :: 3
Classifier: Programming Language :: Python :: 3.9
Classifier: Programming Language :: Python :: 3.10
Classifier: Programming Language :: Python :: 3.11
Classifier: License :: OSI Approved :: GNU General Public License v3 (GPLv3)
Classifier: Operating System :: OS Independent
Classifier: Development Status :: 3 - Alpha
Classifier: Intended Audience :: Developers
Classifier: Intended Audience :: Science/Research
Classifier: Topic :: Scientific/Engineering
Requires-Python: >=3.9
License-File: LICENSE
Requires-Dist: numpy>=2.0.0
Requires-Dist: matplotlib
Requires-Dist: pandas
Requires-Dist: pyrates
Requires-Dist: meson
Provides-Extra: dev
Requires-Dist: pytest; extra == "dev"
Requires-Dist: bump2version; extra == "dev"
